MANIFEST.in
README.md
build.py
pyproject.toml
requirements-dev.txt
requirements.txt
setup.py
test.py
pystatic/casting.py
pystatic/clean.py
pystatic/overload.py
pystatic/private.py
pystatic/types.py
pystatic_language.egg-info/PKG-INFO
pystatic_language.egg-info/SOURCES.txt
pystatic_language.egg-info/dependency_links.txt
pystatic_language.egg-info/requires.txt
pystatic_language.egg-info/top_level.txt