Metadata-Version: 2.1
Name: pystatic-language
Version: 1.1.3
Summary: This package is a collection of methods and classes for making python more secure, robust, and reliable. This could be achieved through the simple usage of decorators, function calls and inheritance of base classes. Generally, this package can make python a programming language, closer to other static-typed languages, without losing python's dynamic powerful features and.
Home-page: https://github.com/Shahaf-F-S/pystatic
Author: Shahaf Frank-Shapir
Author-email: shahaffrs@gmail.com
License: MIT
Classifier: Intended Audience :: Developers
Classifier: License :: OSI Approved :: MIT License
Classifier: Programming Language :: Python
Classifier: Programming Language :: Python :: 3
Classifier: Programming Language :: Python :: 3.8
Classifier: Programming Language :: Python :: 3.9
Classifier: Programming Language :: Python :: 3.10
Classifier: Programming Language :: Python :: 3.11
Classifier: Operating System :: OS Independent
Provides-Extra: dev
